qardl/__init__.py
qardl/__version__.py
qardl/core_corrected.py
qardl/ecm_corrected.py
qardl/lag_selection.py
qardl/rolling_corrected.py
qardl/tests_corrected.py
qardl/utils.py
qardl/visualization.py
qardl-1.0.4.dist-info/licenses/LICENSE
qardl-1.0.4.dist-info/METADATA
qardl-1.0.4.dist-info/WHEEL
qardl-1.0.4.dist-info/top_level.txt
qardl-1.0.4.dist-info/RECORD
